variational_lse_solver/__init__.py
variational_lse_solver/circuits.py
variational_lse_solver/gates.py
variational_lse_solver/utils.py
variational_lse_solver/var_lse_solver.py
variational_lse_solver/cost_function/__init__.py
variational_lse_solver/cost_function/cost_function.py
variational_lse_solver/cost_function/cost_function_helpers.py
variational_lse_solver/cost_function/cost_function_types.py
variational_lse_solver/cost_function/global_fn/__init__.py
variational_lse_solver/cost_function/global_fn/global_base.py
variational_lse_solver/cost_function/global_fn/global_coherent.py
variational_lse_solver/cost_function/global_fn/global_direct.py
variational_lse_solver/cost_function/global_fn/global_hadamard.py
variational_lse_solver/cost_function/global_fn/global_overlap.py
variational_lse_solver/cost_function/local_fn/__init__.py
variational_lse_solver/cost_function/local_fn/local_base.py
variational_lse_solver/cost_function/local_fn/local_direct.py
variational_lse_solver/cost_function/local_fn/local_hadamard.py
variational_lse_solver/cost_function/local_fn/local_overlap.py
variational_lse_solver/cost_function/norm_fn/__init__.py
variational_lse_solver/cost_function/norm_fn/norm_base.py
variational_lse_solver/cost_function/norm_fn/norm_direct.py
variational_lse_solver/cost_function/norm_fn/norm_hadamard.py
variational_lse_solver-1.0.dist-info/LICENSE
variational_lse_solver-1.0.dist-info/METADATA
variational_lse_solver-1.0.dist-info/WHEEL
variational_lse_solver-1.0.dist-info/top_level.txt
variational_lse_solver-1.0.dist-info/RECORD
