Metadata-Version: 2.1
Name: variational-lse-solver
Version: 1.0
Summary: Comprehensive Library of Variational LSE Solvers
Home-page: https://github.com/nicomeyer96/variational-lse-solver
Author: Fraunhofer IIS
Author-email: nico.meyer@iis.fraunhofer.de
License: Apache License 2.0
Classifier: Programming Language :: Python :: 3
Classifier: License :: OSI Approved :: Apache Software License
Classifier: Operating System :: OS Independent
Requires-Python: ~=3.12
License-File: LICENSE
Requires-Dist: pennylane ~=0.34
Requires-Dist: torch ~=2.2.1
Requires-Dist: tqdm ~=4.66.2
